edetek_words/__init__.py
edetek_words/common/calc_time.py
edetek_words/common/constant.py
edetek_words/common/docx_utils.py
edetek_words/common/json_utils.py
edetek_words/common/logger.py
edetek_words/common/path.py
edetek_words/common/read_file.py
edetek_words/common/translate_util.py
edetek_words/common/word_cleaner.py
edetek_words/core/__init__.py
edetek_words/core/build_map.py
edetek_words/core/build_translate_map.py
edetek_words/core/core.py
edetek_words/core/prepare.py
edetek_words/core/word_extractor.py
edetek_words/core/word_replacer.py
edetek_words/docs/CRN04894-13_GC Dosing Diary_v3.0_Final Draft.json
edetek_words/docs/Turkey (Turkish) SF-36v2 Acute Screen Shot Sample.json
edetek_words/docs/payload.json
edetek_words/dto/base_dto.py
edetek_words/dto/segment_dto.py
edetek_words/dto/styled_text_segment.py
edetek_words/dto/translated_dto.py
edetek_words/dto/translation_package.py
edetek_words-1.0.21.dist-info/licenses/LICENSE
edetek_words-1.0.21.dist-info/METADATA
edetek_words-1.0.21.dist-info/WHEEL
edetek_words-1.0.21.dist-info/top_level.txt
edetek_words-1.0.21.dist-info/RECORD
