Metadata-Version: 2.4
Name: edetek_words
Version: 1.0.21
Summary: edetek words
Home-page: http://example.com
Author: xiaodong.li
Author-email: 
Classifier: Programming Language :: Python :: 3.10
License-File: LICENSE
Requires-Dist: python-docx==1.2.0
Requires-Dist: pywin32==311
Requires-Dist: loguru==0.7.3
Requires-Dist: PyYAML==6.0.2
Requires-Dist: lxml==6.0.0
Requires-Dist: requests==2.32.4
Requires-Dist: pycryptodome==3.23.0
Dynamic: author
Dynamic: classifier
Dynamic: description
Dynamic: description-content-type
Dynamic: home-page
Dynamic: license-file
Dynamic: requires-dist
Dynamic: summary
